{
	"images": [
		{
			"startdate": "20200508",
			"fullstartdate": "202005080700",
			"enddate": "20200509",
			"url": "/th?id=OHR.ChampsVEDay_EN-US3938798120_1920x1080.jpg&rf=LaDigue_1920x1080.jpg&pid=hp",
			"urlbase": "/th?id=OHR.ChampsVEDay_EN-US3938798120",
			"copyright": "People looking at the crowded Avenue des Champs-Élysées from the Arc de Triomphe on May 8, 1945, Paris, France (© AFP via Getty Images)",
			"copyrightlink": "https://www.bing.com/search?q=ve+day&form=hpcapt&filters=HpDate%3a%2220200508_0700%22",
			"title": "Victory in Europe, 75 years ago",
			"quiz": "/search?q=Bing+homepage+quiz&filters=WQOskey:%22HPQuiz_20200508_ChampsVEDay%22&FORM=HPQUIZ",
			"wp": false,
			"hsh": "4f1a55d590db160171e475a4ed6099c9",
			"drk": 1,
			"top": 1,
			"bot": 1,
			"hs": []
		},
		{
			"startdate": "20200507",
			"fullstartdate": "202005070700",
			"enddate": "20200508",
			"url": "/th?id=OHR.WildflowerWeek_EN-US0188713175_1920x1080.jpg&rf=LaDigue_1920x1080.jpg&pid=hp",
			"urlbase": "/th?id=OHR.WildflowerWeek_EN-US0188713175",
			"copyright": "Bluebonnets growing alongside an old road in the Texas Hill Country (© Inge Johnsson/Alamy)",
			"copyrightlink": "https://www.bing.com/search?q=texas+bluebonnets&form=hpcapt&filters=HpDate%3a%2220200507_0700%22",
			"title": "Where the wildflowers grow",
			"quiz": "/search?q=Bing+homepage+quiz&filters=WQOskey:%22HPQuiz_20200507_WildflowerWeek%22&FORM=HPQUIZ",
			"wp": true,
			"hsh": "871991f3b848b29216e2b7e01940edfe",
			"drk": 1,
			"top": 1,
			"bot": 1,
			"hs": []
		},
		{
			"startdate": "20200506",
			"fullstartdate": "202005060700",
			"enddate": "20200507",
			"url": "/th?id=OHR.SiegeofCusco_EN-US6660036620_1920x1080.jpg&rf=LaDigue_1920x1080.jpg&pid=hp",
			"urlbase": "/th?id=OHR.SiegeofCusco_EN-US6660036620",
			"copyright": "Inca fortress of Sacsayhuamán near Cusco, Peru (© Susanne Kremer/eStock Photo)",
			"copyrightlink": "https://www.bing.com/search?q=fortress+of+sacsayhuaman&FORM=hpcapt&filters=HpDate%3a%2220200506_0700%22",
			"title": "The (Inca) empire strikes back",
			"quiz": "/search?q=Bing+homepage+quiz&filters=WQOskey:%22HPQuiz_20200506_SiegeofCusco%22&FORM=HPQUIZ",
			"wp": true,
			"hsh": "c41d5cb48a5fe0483de7fe48002301d6",
			"drk": 1,
			"top": 1,
			"bot": 1,
			"hs": []
		},
		{
			"startdate": "20200505",
			"fullstartdate": "202005050700",
			"enddate": "20200506",
			"url": "/th?id=OHR.CordovanCourts_EN-US4311661710_1920x1080.jpg&rf=LaDigue_1920x1080.jpg&pid=hp",
			"urlbase": "/th?id=OHR.CordovanCourts_EN-US4311661710",
			"copyright": "Bronze sculpture of a child and his grandfather caring for plants and flowers in the San Basilio neighborhood of Córdoba, Spain (© David M G/Alamy)",
			"copyrightlink": "https://www.bing.com/search?q=san+basilio+cordoba&FORM=hpcapt&filters=HpDate%3a%2220200505_0700%22",
			"title": "A courtyard scene from Spain",
			"quiz": "/search?q=Bing+homepage+quiz&filters=WQOskey:%22HPQuiz_20200505_CordovanCourts%22&FORM=HPQUIZ",
			"wp": true,
			"hsh": "6b338a28c3aa50478940529c1303dd86",
			"drk": 1,
			"top": 1,
			"bot": 1,
			"hs": []
		},
		{
			"startdate": "20200504",
			"fullstartdate": "202005040700",
			"enddate": "20200505",
			"url": "/th?id=OHR.LastJedi_EN-US6415775481_1920x1080.jpg&rf=LaDigue_1920x1080.jpg&pid=hp",
			"urlbase": "/th?id=OHR.LastJedi_EN-US6415775481",
			"copyright": "Salar de Uyuni, Bolivia (© Ignacio Palacios/Getty Images)",
			"copyrightlink": "https://www.bing.com/search?q=star+wars+day&form=hpcapt&filters=HpDate%3a%2220200504_0700%22",
			"title": "It's Star Wars Day",
			"quiz": "/search?q=Bing+homepage+quiz&filters=WQOskey:%22HPQuiz_20200504_LastJedi%22&FORM=HPQUIZ",
			"wp": true,
			"hsh": "7acf05c245c1f9cb29032b6ac3ab2aaa",
			"drk": 1,
			"top": 1,
			"bot": 1,
			"hs": []
		},
		{
			"startdate": "20200503",
			"fullstartdate": "202005030700",
			"enddate": "20200504",
			"url": "/th?id=OHR.LaughingOwl_EN-US6301340149_1920x1080.jpg&rf=LaDigue_1920x1080.jpg&pid=hp",
			"urlbase": "/th?id=OHR.LaughingOwl_EN-US6301340149",
			"copyright": "Snowy owl at Jones Beach, Long Island, New York (© Vicki Jauron/Getty Images)",
			"copyrightlink": "https://www.bing.com/search?q=snowy+owl+bird&form=hpcapt&filters=HpDate%3a%2220200503_0700%22",
			"title": "World Laughter Day—it's a hoot",
			"quiz": "/search?q=Bing+homepage+quiz&filters=WQOskey:%22HPQuiz_20200503_LaughingOwl%22&FORM=HPQUIZ",
			"wp": true,
			"hsh": "b71a2dfe3977716a0d4762e3497f536d",
			"drk": 1,
			"top": 1,
			"bot": 1,
			"hs": []
		},
		{
			"startdate": "20200502",
			"fullstartdate": "202005020700",
			"enddate": "20200503",
			"url": "/th?id=OHR.KasbahRoses_EN-US6066255132_1920x1080.jpg&rf=LaDigue_1920x1080.jpg&pid=hp",
			"urlbase": "/th?id=OHR.KasbahRoses_EN-US6066255132",
			"copyright": "Ruins of a kasbah in Kalaat M'Gouna, Morocco (© Leonid Andronov/Getty Images)",
			"copyrightlink": "https://www.bing.com/search?q=kalaat+m%27gouna+valley+of+roses&form=hpcapt&filters=HpDate%3a%2220200502_0700%22",
			"title": "Morocco in bloom",
			"quiz": "/search?q=Bing+homepage+quiz&filters=WQOskey:%22HPQuiz_20200502_KasbahRoses%22&FORM=HPQUIZ",
			"wp": true,
			"hsh": "5a921b8c24b19464c5068cd549b1647e",
			"drk": 1,
			"top": 1,
			"bot": 1,
			"hs": []
		},
		{
			"startdate": "20200501",
			"fullstartdate": "202005010700",
			"enddate": "20200502",
			"url": "/th?id=OHR.KubotaGarden_EN-US5986864816_1920x1080.jpg&rf=LaDigue_1920x1080.jpg&pid=hp",
			"urlbase": "/th?id=OHR.KubotaGarden_EN-US5986864816",
			"copyright": "Rhododendrons and azaleas blooming around the Moon Bridge, Kubota Garden, Seattle, Washington (© Mary Liz Austin/Alamy)",
			"copyrightlink": "https://www.bing.com/search?q=kubota+garden+seattle&form=hpcapt&filters=HpDate%3a%2220200501_0700%22",
			"title": "It's Asian Pacific American Heritage Month",
			"quiz": "/search?q=Bing+homepage+quiz&filters=WQOskey:%22HPQuiz_20200501_KubotaGarden%22&FORM=HPQUIZ",
			"wp": true,
			"hsh": "45cb055cc9c2dd704b42502728c80cf3",
			"drk": 1,
			"top": 1,
			"bot": 1,
			"hs": []
		}
	],
	"tooltips": {
		"loading": "Loading...",
		"previous": "Previous image",
		"next": "Next image",
		"walle": "This image is not available to download as wallpaper.",
		"walls": "Download this image. Use of this image is restricted to wallpaper only."
	}
}